file_organizer_sachin23pandey/__init__.py
file_organizer_sachin23pandey/file_organizer.py
file_organizer_sachin23pandey-1.0.0.dist-info/METADATA
file_organizer_sachin23pandey-1.0.0.dist-info/WHEEL
file_organizer_sachin23pandey-1.0.0.dist-info/licenses/LICENCE
file_organizer_sachin23pandey-1.0.0.dist-info/RECORD
