Metadata-Version: 2.4
Name: file_organizer_sachin23pandey
Version: 1.0.0
Summary: This is a file organizer designed to assist users in managing their directories more visually and intuitively
Author-email: Sachin Pandey <pandeysachin8953@gmail.com>
License-Expression: MIT
License-File: LICENCE
Classifier: Operating System :: OS Independent
Classifier: Programming Language :: Python :: 3
Requires-Python: >=3.6
